libmapper/libmapper.so
libmapper/mapper.py
libmapper/__init__.py
libmapper-2.5.1.dist-info/WHEEL
libmapper-2.5.1.dist-info/top_level.txt
libmapper-2.5.1.dist-info/METADATA
libmapper-2.5.1.dist-info/RECORD
libmapper.libs/liblo-5432bd39.so.7.6.1
