Metadata-Version: 2.4
Name: libmapper
Version: 2.5.1
Summary: A library for representing input and output signals on a network and allowing arbitrary 'mappings' to be dynamically created between them.
Home-page: http://libmapper.org
Author: libmapper.org
Author-email: dot_mapper@googlegroups.com
License: GNU LGPL version 2.1 or later
Dynamic: author
Dynamic: author-email
Dynamic: description
Dynamic: description-content-type
Dynamic: home-page
Dynamic: license
Dynamic: summary
